mangono_odoo_clevercloud/__init__.py
mangono_odoo_clevercloud/extensions/__init__.py
mangono_odoo_clevercloud/extensions/cc_auto_config.py
mangono_odoo_clevercloud/mappers/__init__.py
mangono_odoo_clevercloud/mappers/cc_postgresql.py
mangono_odoo_clevercloud-1.0.2.dist-info/METADATA
mangono_odoo_clevercloud-1.0.2.dist-info/WHEEL
mangono_odoo_clevercloud-1.0.2.dist-info/entry_points.txt
mangono_odoo_clevercloud-1.0.2.dist-info/RECORD
