Metadata-Version: 2.4
Name: mangono-odoo-clevercloud
Version: 1.0.2
Classifier: Framework :: Odoo
Classifier: Framework :: Odoo :: 12.0
Classifier: Framework :: Odoo :: 13.0
Classifier: Framework :: Odoo :: 14.0
Classifier: Framework :: Odoo :: 15.0
Classifier: Framework :: Odoo :: 16.0
Classifier: Framework :: Odoo :: 17.0
Classifier: Framework :: Odoo :: 18.0
Classifier: Programming Language :: Python :: 3
Classifier: Programming Language :: Python :: 3 :: Only
Classifier: Programming Language :: Python :: 3.8
Classifier: Programming Language :: Python :: 3.9
Classifier: Programming Language :: Python :: 3.10
Classifier: Programming Language :: Python :: 3.11
Classifier: Programming Language :: Python :: 3.12
Classifier: Typing :: Typed
Requires-Python: >=3.8
Requires-Dist: environ-odoo-config>=0.6.5
Requires-Dist: importlib-metadata>=6.7.0
Requires-Dist: mangono-addon-odoo-cron-patch==0.1.1
Requires-Dist: mangono-addon-odoo-custom-server~=1.2.0
Requires-Dist: mangono-addon-odoo-filestore-s3~=2.2.0
Requires-Dist: mangono-addon-redis-session-store~=2.2.0
